funitroot/__init__.py
funitroot/fourier_adf.py
funitroot/fourier_kpss.py
funitroot/visualization.py
funitroot-1.0.2.dist-info/licenses/LICENSE
funitroot-1.0.2.dist-info/METADATA
funitroot-1.0.2.dist-info/WHEEL
funitroot-1.0.2.dist-info/top_level.txt
funitroot-1.0.2.dist-info/RECORD
