Metadata-Version: 2.4
Name: funitroot
Version: 1.0.2
Summary: Fourier-augmented unit-root tests (ADF, KPSS) with F-tests for linearity
Author-email: "Dr. Merwan Roudane" <merwanroudane920@gmail.com>
License-Expression: MIT
Requires-Python: >=3.8
License-File: LICENSE
Requires-Dist: numpy>=1.20
Requires-Dist: scipy>=1.7
Requires-Dist: pandas>=1.3
Requires-Dist: matplotlib>=3.4
Requires-Dist: statsmodels>=0.13
Dynamic: license-file
